heropytools/__init__.py
heropytools/HeroData/Contour.py
heropytools/HeroData/FunctionSpecification.py
heropytools/HeroData/HeroArray.py
heropytools/HeroData/HeroColumn.py
heropytools/HeroData/HeroContour.py
heropytools/HeroData/HeroData.py
heropytools/HeroData/HeroDataType.py
heropytools/HeroData/HeroImage.py
heropytools/HeroData/HeroList.py
heropytools/HeroData/HeroString.py
heropytools/HeroData/HeroStruct.py
heropytools/HeroData/HeroTable.py
heropytools/HeroData/IODescription.py
heropytools/HeroData/ImageChannelDescription.py
heropytools/HeroData/InputDescription.py
heropytools/HeroData/InputList.py
heropytools/HeroData/NodeIOType.py
heropytools/HeroData/NodeIOUtils.py
heropytools/HeroData/OutputDescription.py
heropytools/HeroData/OutputList.py
heropytools/HeroData/ScanInformation.py
heropytools/HeroData/SettingsBigString.py
heropytools/HeroData/SettingsBool.py
heropytools/HeroData/SettingsBoolArray.py
heropytools/HeroData/SettingsClickButton.py
heropytools/HeroData/SettingsColorMap.py
heropytools/HeroData/SettingsComplex.py
heropytools/HeroData/SettingsComplexArray.py
heropytools/HeroData/SettingsFileString.py
heropytools/HeroData/SettingsFloat.py
heropytools/HeroData/SettingsFloatArray.py
heropytools/HeroData/SettingsGroup.py
heropytools/HeroData/SettingsInteger.py
heropytools/HeroData/SettingsIntegerArray.py
heropytools/HeroData/SettingsItem.py
heropytools/HeroData/SettingsNDArray.py
heropytools/HeroData/SettingsPathString.py
heropytools/HeroData/SettingsSelection.py
heropytools/HeroData/SettingsString.py
heropytools/HeroData/SettingsStringArray.py
heropytools/HeroData/SettingsValue.py
heropytools/HeroData/SettingsValueArray.py
heropytools/HeroData/SettingsValueList.py
heropytools/HeroData/SettingsVector3D.py
heropytools/HeroData/SubjectInformation.py
heropytools/HeroData/Vector3.py
heropytools/HeroData/Version.py
heropytools/HeroData/__init__.py
heropytools/HeroData/CustomSerializers/DataFrameColumnSerializer.py
heropytools-1.3.3.dist-info/LICENSE.txt
heropytools-1.3.3.dist-info/METADATA
heropytools-1.3.3.dist-info/WHEEL
heropytools-1.3.3.dist-info/top_level.txt
heropytools-1.3.3.dist-info/RECORD
