Metadata-Version: 2.1
Name: heropytools
Version: 1.3.3
Summary: A package for interaction with Hero.
Home-page: http://heroimaging.com
Author: Hero Imaging AB
Author-email: contact@heroimaging.com
License: LICENSE.txt
License-File: LICENSE.txt
Requires-Dist: numpy (>=1.22)
Requires-Dist: pandas (>=1.4)
